ojuara.py
fundao-1.0.dist-info/METADATA
fundao-1.0.dist-info/WHEEL
fundao-1.0.dist-info/top_level.txt
fundao-1.0.dist-info/RECORD
