Metadata-Version: 2.1
Name: fundao
Version: 1.0
Summary: Brincando com distribuição python
Home-page: UNKNOWN
Author: Fundao
Author-email: ojuara@araujo.com
License: UNKNOWN
Platform: UNKNOWN
